{
    "sourceFile": "src/component/Header/Header.tsx",
    "activeCommit": 0,
    "commits": [
        {
            "activePatchIndex": 23,
            "patches": [
                {
                    "date": 1731248981264,
                    "content": "Index: \n===================================================================\n--- \n+++ \n"
                },
                {
                    "date": 1731248988876,
                    "content": "Index: \n===================================================================\n--- \n+++ \n@@ -0,0 +1,43 @@\n+\"use client\"; \r\n+\r\n+import Link from \"next/link\";\r\n+import Navb // Assuming Nav is a custom component.\r\n+import MobileNav from \"../MobileNav\"; // Assuming MobileNav is a custom component.\r\n+import Image from \"next/image\"; \r\n+import './Header.css'; // Import the custom CSS for this component\r\n+\r\n+const Header = () => {\r\n+  return (\r\n+    <header className=\"header\">\r\n+      <div className=\"container\">\r\n+\r\n+        {/* Link with Logo Image */}\r\n+        <Link href=\"/\">\r\n+          <Image\r\n+            src=\"/logo.jpeg\" \r\n+            alt=\"Aliza Logo\"\r\n+            width={115} \r\n+            height={60}\r\n+            priority \r\n+          />\r\n+        </Link>\r\n+\r\n+        {/* Navbar */}\r\n+        <div className=\"navbar\">\r\n+          <Nav />\r\n+          <Link href='/contact'>\r\n+            <button className=\"hire-button\">Hire me</button>\r\n+          </Link>\r\n+        </div>\r\n+\r\n+        {/* Mobile Nav */}\r\n+        <div className=\"mobile-nav\"> \r\n+           <MobileNav /> \r\n+        </div>\r\n+\r\n+      </div>\r\n+    </header>\r\n+  );\r\n+};\r\n+\r\n+export default Header;\n\\ No newline at end of file\n"
                },
                {
                    "date": 1731248995273,
                    "content": "Index: \n===================================================================\n--- \n+++ \n@@ -0,0 +1,43 @@\n+\"use client\"; \r\n+\r\n+import Link from \"next/link\";\r\n+import Navbar from \"../Navbar\"; \r\n+import MobileNav from \"../MobileNav\"; // Assuming MobileNav is a custom component.\r\n+import Image from \"next/image\"; \r\n+import './Header.css'; // Import the custom CSS for this component\r\n+\r\n+const Header = () => {\r\n+  return (\r\n+    <header className=\"header\">\r\n+      <div className=\"container\">\r\n+\r\n+        {/* Link with Logo Image */}\r\n+        <Link href=\"/\">\r\n+          <Image\r\n+            src=\"/logo.jpeg\" \r\n+            alt=\"Aliza Logo\"\r\n+            width={115} \r\n+            height={60}\r\n+            priority \r\n+          />\r\n+        </Link>\r\n+\r\n+        {/* Navbar */}\r\n+        <div className=\"navbar\">\r\n+          <Nav />\r\n+          <Link href='/contact'>\r\n+            <button className=\"hire-button\">Hire me</button>\r\n+          </Link>\r\n+        </div>\r\n+\r\n+        {/* Mobile Nav */}\r\n+        <div className=\"mobile-nav\"> \r\n+           <MobileNav /> \r\n+        </div>\r\n+\r\n+      </div>\r\n+    </header>\r\n+  );\r\n+};\r\n+\r\n+export default Header;\n\\ No newline at end of file\n"
                },
                {
                    "date": 1731249003285,
                    "content": "Index: \n===================================================================\n--- \n+++ \n@@ -0,0 +1,43 @@\n+\"use client\"; \r\n+\r\n+import Link from \"next/link\";\r\n+import Navbar from \"../Navbar\"; \r\n+import MobileNav from \"../MobileNav\"; // Assuming MobileNav is a custom component.\r\n+import Image from \"next/image\"; \r\n+import './Header.css'; \r\n+\r\n+const Header = () => {\r\n+  return (\r\n+    <header className=\"header\">\r\n+      <div className=\"container\">\r\n+\r\n+        {/* Link with Logo Image */}\r\n+        <Link href=\"/\">\r\n+          <Image\r\n+            src=\"/logo.jpeg\" \r\n+            alt=\"Aliza Logo\"\r\n+            width={115} \r\n+            height={60}\r\n+            priority \r\n+          />\r\n+        </Link>\r\n+\r\n+        {/* Navbar */}\r\n+        <div className=\"navbar\">\r\n+          <Navbar />\r\n+          <Link href='/contact'>\r\n+            <button className=\"hire-button\">Hire me</button>\r\n+          </Link>\r\n+        </div>\r\n+\r\n+        {/* Mobile Nav */}\r\n+        <div className=\"mobile-nav\"> \r\n+           <MobileNav /> \r\n+        </div>\r\n+\r\n+      </div>\r\n+    </header>\r\n+  );\r\n+};\r\n+\r\n+export default Header;\n\\ No newline at end of file\n"
                },
                {
                    "date": 1731249039869,
                    "content": "Index: \n===================================================================\n--- \n+++ \n@@ -0,0 +1,42 @@\n+\"use client\"; \r\n+\r\n+import Link from \"next/link\";\r\n+import Navbar from \"../Navbar\"; \r\n+import Image from \"next/image\"; \r\n+import './Header.css'; \r\n+\r\n+const Header = () => {\r\n+  return (\r\n+    <header className=\"header\">\r\n+      <div className=\"container\">\r\n+\r\n+        {/* Link with Logo Image */}\r\n+        <Link href=\"/\">\r\n+          <Image\r\n+            src=\"/logo.jpeg\" \r\n+            alt=\"Aliza Logo\"\r\n+            width={115} \r\n+            height={60}\r\n+            priority \r\n+          />\r\n+        </Link>\r\n+\r\n+        {/* Navbar */}\r\n+        <div className=\"navbar\">\r\n+          <Navbar />\r\n+          <Link href='/contact'>\r\n+            <button className=\"hire-button\">Hire me</button>\r\n+          </Link>\r\n+        </div>\r\n+\r\n+        {/* Mobile Nav */}\r\n+        <div className=\"mobile-nav\"> \r\n+           <MobileNav /> \r\n+        </div>\r\n+\r\n+      </div>\r\n+    </header>\r\n+  );\r\n+};\r\n+\r\n+export default Header;\n\\ No newline at end of file\n"
                },
                {
                    "date": 1731249137264,
                    "content": "Index: \n===================================================================\n--- \n+++ \n@@ -0,0 +1,37 @@\n+\"use client\"; \r\n+\r\n+import Link from \"next/link\";\r\n+import Navbar from \"../Navbar\"; \r\n+import Image from \"next/image\"; \r\n+import './Header.css'; \r\n+\r\n+const Header = () => {\r\n+  return (\r\n+    <header className=\"header\">\r\n+      <div className=\"container\">\r\n+\r\n+        {/* Link with Logo Image */}\r\n+        <Link href=\"/\">\r\n+          <Image\r\n+            src=\"/logo.jpeg\" \r\n+            alt=\"Aliza Logo\"\r\n+            width={115} \r\n+            height={60}\r\n+            priority \r\n+          />\r\n+        </Link>\r\n+\r\n+        {/* Navbar */}\r\n+        <div className=\"navbar\">\r\n+          <Navbar />\r\n+          <Link href='/contact'>\r\n+            <button className=\"hire-button\">Hire me</button>\r\n+          </Link>\r\n+        </div>\r\n+\r\n+      </div>\r\n+    </header>\r\n+  );\r\n+};\r\n+\r\n+export default Header;\n\\ No newline at end of file\n"
                },
                {
                    "date": 1731249291737,
                    "content": "Index: \n===================================================================\n--- \n+++ \n@@ -1,8 +1,8 @@\n \"use client\"; \r\n \r\n import Link from \"next/link\";\r\n-import Navbar from \"../Navbar\"; \r\n+import Navbar\r\n import Image from \"next/image\"; \r\n import './Header.css'; \r\n \r\n const Header = () => {\r\n"
                },
                {
                    "date": 1731249297197,
                    "content": "Index: \n===================================================================\n--- \n+++ \n@@ -1,8 +1,8 @@\n \"use client\"; \r\n \r\n import Link from \"next/link\";\r\n-import Navbar\r\n+import NA\r\n import Image from \"next/image\"; \r\n import './Header.css'; \r\n \r\n const Header = () => {\r\n@@ -33,219 +33,5 @@\n     </header>\r\n   );\r\n };\r\n \r\n-export default Header;\n-\"use client\"; \r\n-\r\n-import Link from \"next/link\";\r\n-import Navbar from \"../Navbar\"; \r\n-import Image from \"next/image\"; \r\n-import './Header.css'; \r\n-\r\n-const Header = () => {\r\n-  return (\r\n-    <header className=\"header\">\r\n-      <div className=\"container\">\r\n-\r\n-        {/* Link with Logo Image */}\r\n-        <Link href=\"/\">\r\n-          <Image\r\n-            src=\"/logo.jpeg\" \r\n-            alt=\"Aliza Logo\"\r\n-            width={115} \r\n-            height={60}\r\n-            priority \r\n-          />\r\n-        </Link>\r\n-\r\n-        {/* Navbar */}\r\n-        <div className=\"navbar\">\r\n-          <Navbar />\r\n-          <Link href='/contact'>\r\n-            <button className=\"hire-button\">Hire me</button>\r\n-          </Link>\r\n-        </div>\r\n-\r\n-        {/* Mobile Nav */}\r\n-        <div className=\"mobile-nav\"> \r\n-           <MobileNav /> \r\n-        </div>\r\n-\r\n-      </div>\r\n-    </header>\r\n-  );\r\n-};\r\n-\r\n-export default Header;\n-\"use client\"; \r\n-\r\n-import Link from \"next/link\";\r\n-import Navbar from \"../Navbar\"; \r\n-import MobileNav from \"../MobileNav\"; // Assuming MobileNav is a custom component.\r\n-import Image from \"next/image\"; \r\n-import './Header.css'; \r\n-\r\n-const Header = () => {\r\n-  return (\r\n-    <header className=\"header\">\r\n-      <div className=\"container\">\r\n-\r\n-        {/* Link with Logo Image */}\r\n-        <Link href=\"/\">\r\n-          <Image\r\n-            src=\"/logo.jpeg\" \r\n-            alt=\"Aliza Logo\"\r\n-            width={115} \r\n-            height={60}\r\n-            priority \r\n-          />\r\n-        </Link>\r\n-\r\n-        {/* Navbar */}\r\n-        <div className=\"navbar\">\r\n-          <Navbar />\r\n-          <Link href='/contact'>\r\n-            <button className=\"hire-button\">Hire me</button>\r\n-          </Link>\r\n-        </div>\r\n-\r\n-        {/* Mobile Nav */}\r\n-        <div className=\"mobile-nav\"> \r\n-           <MobileNav /> \r\n-        </div>\r\n-\r\n-      </div>\r\n-    </header>\r\n-  );\r\n-};\r\n-\r\n-export default Header;\n-\"use client\"; \r\n-\r\n-import Link from \"next/link\";\r\n-import Navbar from \"../Navbar\"; \r\n-import MobileNav from \"../MobileNav\"; // Assuming MobileNav is a custom component.\r\n-import Image from \"next/image\"; \r\n-import './Header.css'; // Import the custom CSS for this component\r\n-\r\n-const Header = () => {\r\n-  return (\r\n-    <header className=\"header\">\r\n-      <div className=\"container\">\r\n-\r\n-        {/* Link with Logo Image */}\r\n-        <Link href=\"/\">\r\n-          <Image\r\n-            src=\"/logo.jpeg\" \r\n-            alt=\"Aliza Logo\"\r\n-            width={115} \r\n-            height={60}\r\n-            priority \r\n-          />\r\n-        </Link>\r\n-\r\n-        {/* Navbar */}\r\n-        <div className=\"navbar\">\r\n-          <Nav />\r\n-          <Link href='/contact'>\r\n-            <button className=\"hire-button\">Hire me</button>\r\n-          </Link>\r\n-        </div>\r\n-\r\n-        {/* Mobile Nav */}\r\n-        <div className=\"mobile-nav\"> \r\n-           <MobileNav /> \r\n-        </div>\r\n-\r\n-      </div>\r\n-    </header>\r\n-  );\r\n-};\r\n-\r\n-export default Header;\n-\"use client\"; \r\n-\r\n-import Link from \"next/link\";\r\n-import Navb // Assuming Nav is a custom component.\r\n-import MobileNav from \"../MobileNav\"; // Assuming MobileNav is a custom component.\r\n-import Image from \"next/image\"; \r\n-import './Header.css'; // Import the custom CSS for this component\r\n-\r\n-const Header = () => {\r\n-  return (\r\n-    <header className=\"header\">\r\n-      <div className=\"container\">\r\n-\r\n-        {/* Link with Logo Image */}\r\n-        <Link href=\"/\">\r\n-          <Image\r\n-            src=\"/logo.jpeg\" \r\n-            alt=\"Aliza Logo\"\r\n-            width={115} \r\n-            height={60}\r\n-            priority \r\n-          />\r\n-        </Link>\r\n-\r\n-        {/* Navbar */}\r\n-        <div className=\"navbar\">\r\n-          <Nav />\r\n-          <Link href='/contact'>\r\n-            <button className=\"hire-button\">Hire me</button>\r\n-          </Link>\r\n-        </div>\r\n-\r\n-        {/* Mobile Nav */}\r\n-        <div className=\"mobile-nav\"> \r\n-           <MobileNav /> \r\n-        </div>\r\n-\r\n-      </div>\r\n-    </header>\r\n-  );\r\n-};\r\n-\r\n-export default Header;\n-\"use client\"; \r\n-\r\n-import Link from \"next/link\";\r\n-import Nav from \"../Nav/Navbar\"; // Assuming Nav is a custom component.\r\n-import MobileNav from \"../MobileNav\"; // Assuming MobileNav is a custom component.\r\n-import Image from \"next/image\"; \r\n-import './Header.css'; // Import the custom CSS for this component\r\n-\r\n-const Header = () => {\r\n-  return (\r\n-    <header className=\"header\">\r\n-      <div className=\"container\">\r\n-\r\n-        {/* Link with Logo Image */}\r\n-        <Link href=\"/\">\r\n-          <Image\r\n-            src=\"/logo.jpeg\" \r\n-            alt=\"Aliza Logo\"\r\n-            width={115} \r\n-            height={60}\r\n-            priority \r\n-          />\r\n-        </Link>\r\n-\r\n-        {/* Navbar */}\r\n-        <div className=\"navbar\">\r\n-          <Nav />\r\n-          <Link href='/contact'>\r\n-            <button className=\"hire-button\">Hire me</button>\r\n-          </Link>\r\n-        </div>\r\n-\r\n-        {/* Mobile Nav */}\r\n-        <div className=\"mobile-nav\"> \r\n-           <MobileNav /> \r\n-        </div>\r\n-\r\n-      </div>\r\n-    </header>\r\n-  );\r\n-};\r\n-\r\n export default Header;\n\\ No newline at end of file\n"
                },
                {
                    "date": 1731249306174,
                    "content": "Index: \n===================================================================\n--- \n+++ \n@@ -0,0 +1,37 @@\n+\"use client\"; \r\n+\r\n+import Link from \"next/link\";\r\n+import Navba\r\n+import Image from \"next/image\"; \r\n+import './Header.css'; \r\n+\r\n+const Header = () => {\r\n+  return (\r\n+    <header className=\"header\">\r\n+      <div className=\"container\">\r\n+\r\n+        {/* Link with Logo Image */}\r\n+        <Link href=\"/\">\r\n+          <Image\r\n+            src=\"/logo.jpeg\" \r\n+            alt=\"Aliza Logo\"\r\n+            width={115} \r\n+            height={60}\r\n+            priority \r\n+          />\r\n+        </Link>\r\n+\r\n+        {/* Navbar */}\r\n+        <div className=\"navbar\">\r\n+          <Navbar />\r\n+          <Link href='/contact'>\r\n+            <button className=\"hire-button\">Hire me</button>\r\n+          </Link>\r\n+        </div>\r\n+\r\n+      </div>\r\n+    </header>\r\n+  );\r\n+};\r\n+\r\n+export default Header;\n\\ No newline at end of file\n"
                },
                {
                    "date": 1731249315344,
                    "content": "Index: \n===================================================================\n--- \n+++ \n@@ -0,0 +1,37 @@\n+\"use client\"; \r\n+\r\n+import Link from \"next/link\";\r\n+import Nav from \"../Navbar/Navbar\";\r\n+import Image from \"next/image\"; \r\n+import './Header.css'; \r\n+\r\n+const Header = () => {\r\n+  return (\r\n+    <header className=\"header\">\r\n+      <div className=\"container\">\r\n+\r\n+        {/* Link with Logo Image */}\r\n+        <Link href=\"/\">\r\n+          <Image\r\n+            src=\"/logo.jpeg\" \r\n+            alt=\"Aliza Logo\"\r\n+            width={115} \r\n+            height={60}\r\n+            priority \r\n+          />\r\n+        </Link>\r\n+\r\n+        {/* Navbar */}\r\n+        <div className=\"navbar\">\r\n+          \r\n+          <Link href='/contact'>\r\n+            <button className=\"hire-button\">Hire me</button>\r\n+          </Link>\r\n+        </div>\r\n+\r\n+      </div>\r\n+    </header>\r\n+  );\r\n+};\r\n+\r\n+export default Header;\n\\ No newline at end of file\n"
                },
                {
                    "date": 1731249322392,
                    "content": "Index: \n===================================================================\n--- \n+++ \n@@ -0,0 +1,37 @@\n+\"use client\"; \r\n+\r\n+import Link from \"next/link\";\r\n+import Nav\r\n+import Image from \"next/image\"; \r\n+import './Header.css'; \r\n+\r\n+const Header = () => {\r\n+  return (\r\n+    <header className=\"header\">\r\n+      <div className=\"container\">\r\n+\r\n+        {/* Link with Logo Image */}\r\n+        <Link href=\"/\">\r\n+          <Image\r\n+            src=\"/logo.jpeg\" \r\n+            alt=\"Aliza Logo\"\r\n+            width={115} \r\n+            height={60}\r\n+            priority \r\n+          />\r\n+        </Link>\r\n+\r\n+        {/* Navbar */}\r\n+        <div className=\"navbar\">\r\n+          \r\n+          <Link href='/contact'>\r\n+            <button className=\"hire-button\">Hire me</button>\r\n+          </Link>\r\n+        </div>\r\n+\r\n+      </div>\r\n+    </header>\r\n+  );\r\n+};\r\n+\r\n+export default Header;\n\\ No newline at end of file\n"
                },
                {
                    "date": 1731249331001,
                    "content": "Index: \n===================================================================\n--- \n+++ \n@@ -0,0 +1,37 @@\n+\"use client\"; \r\n+\r\n+import Link from \"next/link\";\r\n+import Navb\r\n+import Image from \"next/image\"; \r\n+import './Header.css'; \r\n+\r\n+const Header = () => {\r\n+  return (\r\n+    <header className=\"header\">\r\n+      <div className=\"container\">\r\n+\r\n+        {/* Link with Logo Image */}\r\n+        <Link href=\"/\">\r\n+          <Image\r\n+            src=\"/logo.jpeg\" \r\n+            alt=\"Aliza Logo\"\r\n+            width={115} \r\n+            height={60}\r\n+            priority \r\n+          />\r\n+        </Link>\r\n+\r\n+        {/* Navbar */}\r\n+        <div className=\"navbar\">\r\n+          \r\n+          <Link href='/contact'>\r\n+            <button className=\"hire-button\">Hire me</button>\r\n+          </Link>\r\n+        </div>\r\n+\r\n+      </div>\r\n+    </header>\r\n+  );\r\n+};\r\n+\r\n+export default Header;\n\\ No newline at end of file\n"
                },
                {
                    "date": 1731249341959,
                    "content": "Index: \n===================================================================\n--- \n+++ \n@@ -0,0 +1,37 @@\n+\"use client\"; \r\n+\r\n+import Link from \"next/link\";\r\n+import Nav\r\n+import Image from \"next/image\"; \r\n+import './Header.css'; \r\n+\r\n+const Header = () => {\r\n+  return (\r\n+    <header className=\"header\">\r\n+      <div className=\"container\">\r\n+\r\n+        {/* Link with Logo Image */}\r\n+        <Link href=\"/\">\r\n+          <Image\r\n+            src=\"/logo.jpeg\" \r\n+            alt=\"Aliza Logo\"\r\n+            width={115} \r\n+            height={60}\r\n+            priority \r\n+          />\r\n+        </Link>\r\n+\r\n+        {/* Navbar */}\r\n+        <div className=\"navbar\">\r\n+          \r\n+          <Link href='/contact'>\r\n+            <button className=\"hire-button\">Hire me</button>\r\n+          </Link>\r\n+        </div>\r\n+\r\n+      </div>\r\n+    </header>\r\n+  );\r\n+};\r\n+\r\n+export default Header;\n\\ No newline at end of file\n"
                },
                {
                    "date": 1731249364002,
                    "content": "Index: \n===================================================================\n--- \n+++ \n@@ -1,8 +1,8 @@\n \"use client\"; \r\n \r\n import Link from \"next/link\";\r\n-import Nav from \"../Navbar/Navbar\";\r\n+import Nav from \"../Nav/Navbar\";\r\n import Image from \"next/image\"; \r\n import './Header.css'; \r\n \r\n const Header = () => {\r\n"
                },
                {
                    "date": 1731249369650,
                    "content": "Index: \n===================================================================\n--- \n+++ \n@@ -0,0 +1,37 @@\n+\"use client\"; \r\n+\r\n+import Link from \"next/link\";\r\n+import Na\r\n+import Image from \"next/image\"; \r\n+import './Header.css'; \r\n+\r\n+const Header = () => {\r\n+  return (\r\n+    <header className=\"header\">\r\n+      <div className=\"container\">\r\n+\r\n+        {/* Link with Logo Image */}\r\n+        <Link href=\"/\">\r\n+          <Image\r\n+            src=\"/logo.jpeg\" \r\n+            alt=\"Aliza Logo\"\r\n+            width={115} \r\n+            height={60}\r\n+            priority \r\n+          />\r\n+        </Link>\r\n+\r\n+        {/* Navbar */}\r\n+        <div className=\"navbar\">\r\n+          \r\n+          <Link href='/contact'>\r\n+            <button className=\"hire-button\">Hire me</button>\r\n+          </Link>\r\n+        </div>\r\n+\r\n+      </div>\r\n+    </header>\r\n+  );\r\n+};\r\n+\r\n+export default Header;\n\\ No newline at end of file\n"
                },
                {
                    "date": 1731249375545,
                    "content": "Index: \n===================================================================\n--- \n+++ \n@@ -0,0 +1,37 @@\n+\"use client\"; \r\n+\r\n+import Link from \"next/link\";\r\n+import Nav from \"../Nav/Navbar\";\r\n+import Image from \"next/image\"; \r\n+import './Header.css'; \r\n+\r\n+const Header = () => {\r\n+  return (\r\n+    <header className=\"header\">\r\n+      <div className=\"container\">\r\n+\r\n+        {/* Link with Logo Image */}\r\n+        <Link href=\"/\">\r\n+          <Image\r\n+            src=\"/logo.jpeg\" \r\n+            alt=\"Aliza Logo\"\r\n+            width={115} \r\n+            height={60}\r\n+            priority \r\n+          />\r\n+        </Link>\r\n+\r\n+        {/* Navbar */}\r\n+        <div className=\"navbar\">\r\n+           <\r\n+          <Link href='/contact'>\r\n+            <button className=\"hire-button\">Hire me</button>\r\n+          </Link>\r\n+        </div>\r\n+\r\n+      </div>\r\n+    </header>\r\n+  );\r\n+};\r\n+\r\n+export default Header;\n\\ No newline at end of file\n"
                },
                {
                    "date": 1731249383977,
                    "content": "Index: \n===================================================================\n--- \n+++ \n@@ -0,0 +1,37 @@\n+\"use client\"; \r\n+\r\n+import Link from \"next/link\";\r\n+import Nav from \"../Nav/Navbar\";\r\n+import Image from \"next/image\"; \r\n+import './Header.css'; \r\n+\r\n+const Header = () => {\r\n+  return (\r\n+    <header className=\"header\">\r\n+      <div className=\"container\">\r\n+\r\n+        {/* Link with Logo Image */}\r\n+        <Link href=\"/\">\r\n+          <Image\r\n+            src=\"/logo.jpeg\" \r\n+            alt=\"Aliza Logo\"\r\n+            width={115} \r\n+            height={60}\r\n+            priority \r\n+          />\r\n+        </Link>\r\n+\r\n+        {/* Navbar */}\r\n+        <div className=\"navbar\">\r\n+           <Navbar />\r\n+          <Link href='/contact'>\r\n+            <button className=\"hire-button\">Hire me</button>\r\n+          </Link>\r\n+        </div>\r\n+\r\n+      </div>\r\n+    </header>\r\n+  );\r\n+};\r\n+\r\n+export default Header;\n\\ No newline at end of file\n"
                },
                {
                    "date": 1731249395276,
                    "content": "Index: \n===================================================================\n--- \n+++ \n@@ -0,0 +1,37 @@\n+\"use client\"; \r\n+\r\n+import Link from \"next/link\";\r\n+import Nav from \"../Nav/Navbar\";\r\n+import Image from \"next/image\"; \r\n+import './Header.css'; \r\n+\r\n+const Header = () => {\r\n+  return (\r\n+    <header className=\"header\">\r\n+      <div className=\"container\">\r\n+\r\n+        {/* Link with Logo Image */}\r\n+        <Link href=\"/\">\r\n+          <Image\r\n+            src=\"/logo.jpeg\" \r\n+            alt=\"Aliza Logo\"\r\n+            width={115} \r\n+            height={60}\r\n+            priority \r\n+          />\r\n+        </Link>\r\n+\r\n+        {/* Navbar */}\r\n+        <div className=\"navbar\">\r\n+           <Nav />\r\n+          <Link href='/contact'>\r\n+            <button className=\"hire-button\">Hire me</button>\r\n+          </Link>\r\n+        </div>\r\n+\r\n+      </div>\r\n+    </header>\r\n+  );\r\n+};\r\n+\r\n+export default Header;\n\\ No newline at end of file\n"
                },
                {
                    "date": 1731253584102,
                    "content": "Index: \n===================================================================\n--- \n+++ \n@@ -2,9 +2,9 @@\n \r\n import Link from \"next/link\";\r\n import Nav from \"../Nav/Navbar\";\r\n import Image from \"next/image\"; \r\n-import './Header.css'; \r\n+import './globals.css'; \r\n \r\n const Header = () => {\r\n   return (\r\n     <header className=\"header\">\r\n@@ -33,338 +33,5 @@\n     </header>\r\n   );\r\n };\r\n \r\n-export default Header;\n-\"use client\"; \r\n-\r\n-import Link from \"next/link\";\r\n-import Nav from \"../Nav/Navbar\";\r\n-import Image from \"next/image\"; \r\n-import './Header.css'; \r\n-\r\n-const Header = () => {\r\n-  return (\r\n-    <header className=\"header\">\r\n-      <div className=\"container\">\r\n-\r\n-        {/* Link with Logo Image */}\r\n-        <Link href=\"/\">\r\n-          <Image\r\n-            src=\"/logo.jpeg\" \r\n-            alt=\"Aliza Logo\"\r\n-            width={115} \r\n-            height={60}\r\n-            priority \r\n-          />\r\n-        </Link>\r\n-\r\n-        {/* Navbar */}\r\n-        <div className=\"navbar\">\r\n-           <Navbar />\r\n-          <Link href='/contact'>\r\n-            <button className=\"hire-button\">Hire me</button>\r\n-          </Link>\r\n-        </div>\r\n-\r\n-      </div>\r\n-    </header>\r\n-  );\r\n-};\r\n-\r\n-export default Header;\n-\"use client\"; \r\n-\r\n-import Link from \"next/link\";\r\n-import Nav from \"../Nav/Navbar\";\r\n-import Image from \"next/image\"; \r\n-import './Header.css'; \r\n-\r\n-const Header = () => {\r\n-  return (\r\n-    <header className=\"header\">\r\n-      <div className=\"container\">\r\n-\r\n-        {/* Link with Logo Image */}\r\n-        <Link href=\"/\">\r\n-          <Image\r\n-            src=\"/logo.jpeg\" \r\n-            alt=\"Aliza Logo\"\r\n-            width={115} \r\n-            height={60}\r\n-            priority \r\n-          />\r\n-        </Link>\r\n-\r\n-        {/* Navbar */}\r\n-        <div className=\"navbar\">\r\n-           <\r\n-          <Link href='/contact'>\r\n-            <button className=\"hire-button\">Hire me</button>\r\n-          </Link>\r\n-        </div>\r\n-\r\n-      </div>\r\n-    </header>\r\n-  );\r\n-};\r\n-\r\n-export default Header;\n-\"use client\"; \r\n-\r\n-import Link from \"next/link\";\r\n-import Na\r\n-import Image from \"next/image\"; \r\n-import './Header.css'; \r\n-\r\n-const Header = () => {\r\n-  return (\r\n-    <header className=\"header\">\r\n-      <div className=\"container\">\r\n-\r\n-        {/* Link with Logo Image */}\r\n-        <Link href=\"/\">\r\n-          <Image\r\n-            src=\"/logo.jpeg\" \r\n-            alt=\"Aliza Logo\"\r\n-            width={115} \r\n-            height={60}\r\n-            priority \r\n-          />\r\n-        </Link>\r\n-\r\n-        {/* Navbar */}\r\n-        <div className=\"navbar\">\r\n-          \r\n-          <Link href='/contact'>\r\n-            <button className=\"hire-button\">Hire me</button>\r\n-          </Link>\r\n-        </div>\r\n-\r\n-      </div>\r\n-    </header>\r\n-  );\r\n-};\r\n-\r\n-export default Header;\n-\"use client\"; \r\n-\r\n-import Link from \"next/link\";\r\n-import Nav\r\n-import Image from \"next/image\"; \r\n-import './Header.css'; \r\n-\r\n-const Header = () => {\r\n-  return (\r\n-    <header className=\"header\">\r\n-      <div className=\"container\">\r\n-\r\n-        {/* Link with Logo Image */}\r\n-        <Link href=\"/\">\r\n-          <Image\r\n-            src=\"/logo.jpeg\" \r\n-            alt=\"Aliza Logo\"\r\n-            width={115} \r\n-            height={60}\r\n-            priority \r\n-          />\r\n-        </Link>\r\n-\r\n-        {/* Navbar */}\r\n-        <div className=\"navbar\">\r\n-          \r\n-          <Link href='/contact'>\r\n-            <button className=\"hire-button\">Hire me</button>\r\n-          </Link>\r\n-        </div>\r\n-\r\n-      </div>\r\n-    </header>\r\n-  );\r\n-};\r\n-\r\n-export default Header;\n-\"use client\"; \r\n-\r\n-import Link from \"next/link\";\r\n-import Navb\r\n-import Image from \"next/image\"; \r\n-import './Header.css'; \r\n-\r\n-const Header = () => {\r\n-  return (\r\n-    <header className=\"header\">\r\n-      <div className=\"container\">\r\n-\r\n-        {/* Link with Logo Image */}\r\n-        <Link href=\"/\">\r\n-          <Image\r\n-            src=\"/logo.jpeg\" \r\n-            alt=\"Aliza Logo\"\r\n-            width={115} \r\n-            height={60}\r\n-            priority \r\n-          />\r\n-        </Link>\r\n-\r\n-        {/* Navbar */}\r\n-        <div className=\"navbar\">\r\n-          \r\n-          <Link href='/contact'>\r\n-            <button className=\"hire-button\">Hire me</button>\r\n-          </Link>\r\n-        </div>\r\n-\r\n-      </div>\r\n-    </header>\r\n-  );\r\n-};\r\n-\r\n-export default Header;\n-\"use client\"; \r\n-\r\n-import Link from \"next/link\";\r\n-import Nav\r\n-import Image from \"next/image\"; \r\n-import './Header.css'; \r\n-\r\n-const Header = () => {\r\n-  return (\r\n-    <header className=\"header\">\r\n-      <div className=\"container\">\r\n-\r\n-        {/* Link with Logo Image */}\r\n-        <Link href=\"/\">\r\n-          <Image\r\n-            src=\"/logo.jpeg\" \r\n-            alt=\"Aliza Logo\"\r\n-            width={115} \r\n-            height={60}\r\n-            priority \r\n-          />\r\n-        </Link>\r\n-\r\n-        {/* Navbar */}\r\n-        <div className=\"navbar\">\r\n-          \r\n-          <Link href='/contact'>\r\n-            <button className=\"hire-button\">Hire me</button>\r\n-          </Link>\r\n-        </div>\r\n-\r\n-      </div>\r\n-    </header>\r\n-  );\r\n-};\r\n-\r\n-export default Header;\n-\"use client\"; \r\n-\r\n-import Link from \"next/link\";\r\n-import Nav from \"../Nav/Navbar\";\r\n-import Image from \"next/image\"; \r\n-import './Header.css'; \r\n-\r\n-const Header = () => {\r\n-  return (\r\n-    <header className=\"header\">\r\n-      <div className=\"container\">\r\n-\r\n-        {/* Link with Logo Image */}\r\n-        <Link href=\"/\">\r\n-          <Image\r\n-            src=\"/logo.jpeg\" \r\n-            alt=\"Aliza Logo\"\r\n-            width={115} \r\n-            height={60}\r\n-            priority \r\n-          />\r\n-        </Link>\r\n-\r\n-        {/* Navbar */}\r\n-        <div className=\"navbar\">\r\n-          \r\n-          <Link href='/contact'>\r\n-            <button className=\"hire-button\">Hire me</button>\r\n-          </Link>\r\n-        </div>\r\n-\r\n-      </div>\r\n-    </header>\r\n-  );\r\n-};\r\n-\r\n-export default Header;\n-\"use client\"; \r\n-\r\n-import Link from \"next/link\";\r\n-import Navba\r\n-import Image from \"next/image\"; \r\n-import './Header.css'; \r\n-\r\n-const Header = () => {\r\n-  return (\r\n-    <header className=\"header\">\r\n-      <div className=\"container\">\r\n-\r\n-        {/* Link with Logo Image */}\r\n-        <Link href=\"/\">\r\n-          <Image\r\n-            src=\"/logo.jpeg\" \r\n-            alt=\"Aliza Logo\"\r\n-            width={115} \r\n-            height={60}\r\n-            priority \r\n-          />\r\n-        </Link>\r\n-\r\n-        {/* Navbar */}\r\n-        <div className=\"navbar\">\r\n-          <Navbar />\r\n-          <Link href='/contact'>\r\n-            <button className=\"hire-button\">Hire me</button>\r\n-          </Link>\r\n-        </div>\r\n-\r\n-      </div>\r\n-    </header>\r\n-  );\r\n-};\r\n-\r\n-export default Header;\n-\"use client\"; \r\n-\r\n-import Link from \"next/link\";\r\n-import NA\r\n-import Image from \"next/image\"; \r\n-import './Header.css'; \r\n-\r\n-const Header = () => {\r\n-  return (\r\n-    <header className=\"header\">\r\n-      <div className=\"container\">\r\n-\r\n-        {/* Link with Logo Image */}\r\n-        <Link href=\"/\">\r\n-          <Image\r\n-            src=\"/logo.jpeg\" \r\n-            alt=\"Aliza Logo\"\r\n-            width={115} \r\n-            height={60}\r\n-            priority \r\n-          />\r\n-        </Link>\r\n-\r\n-        {/* Navbar */}\r\n-        <div className=\"navbar\">\r\n-          <Navbar />\r\n-          <Link href='/contact'>\r\n-            <button className=\"hire-button\">Hire me</button>\r\n-          </Link>\r\n-        </div>\r\n-\r\n-      </div>\r\n-    </header>\r\n-  );\r\n-};\r\n-\r\n export default Header;\n\\ No newline at end of file\n"
                },
                {
                    "date": 1731253714438,
                    "content": "Index: \n===================================================================\n--- \n+++ \n@@ -1,37 +0,0 @@\n-\"use client\"; \r\n-\r\n-import Link from \"next/link\";\r\n-import Nav from \"../Nav/Navbar\";\r\n-import Image from \"next/image\"; \r\n-import './globals.css'; \r\n-\r\n-const Header = () => {\r\n-  return (\r\n-    <header className=\"header\">\r\n-      <div className=\"container\">\r\n-\r\n-        {/* Link with Logo Image */}\r\n-        <Link href=\"/\">\r\n-          <Image\r\n-            src=\"/logo.jpeg\" \r\n-            alt=\"Aliza Logo\"\r\n-            width={115} \r\n-            height={60}\r\n-            priority \r\n-          />\r\n-        </Link>\r\n-\r\n-        {/* Navbar */}\r\n-        <div className=\"navbar\">\r\n-           <Nav />\r\n-          <Link href='/contact'>\r\n-            <button className=\"hire-button\">Hire me</button>\r\n-          </Link>\r\n-        </div>\r\n-\r\n-      </div>\r\n-    </header>\r\n-  );\r\n-};\r\n-\r\n-export default Header;\n\\ No newline at end of file\n"
                },
                {
                    "date": 1731253720605,
                    "content": "Index: \n===================================================================\n--- \n+++ \n@@ -0,0 +1,35 @@\n+// Header.js\r\n+\"use client\";\r\n+\r\n+import Link from \"next/link\";\r\n+import Nav from \"../Nav/Navbar\";\r\n+import Image from \"next/image\";\r\n+\r\n+const Header = () => {\r\n+  return (\r\n+    <header className=\"header\">\r\n+      <div className=\"container\">\r\n+        {/* Link with Logo Image */}\r\n+        <Link href=\"/\">\r\n+          <Image\r\n+            src=\"/logo.jpeg\"\r\n+            alt=\"Aliza Logo\"\r\n+            width={115}\r\n+            height={60}\r\n+            priority\r\n+          />\r\n+        </Link>\r\n+\r\n+        {/* Navbar */}\r\n+        <div className=\"navbar\">\r\n+          <Nav />\r\n+          <Link href=\"/contact\">\r\n+            <button className=\"hire-button\">Hire me</button>\r\n+          </Link>\r\n+        </div>\r\n+      </div>\r\n+    </header>\r\n+  );\r\n+};\r\n+\r\n+export default Header;\n\\ No newline at end of file\n"
                },
                {
                    "date": 1731253726625,
                    "content": "Index: \n===================================================================\n--- \n+++ \n@@ -1,5 +1,4 @@\n-// Header.js\r\n \"use client\";\r\n \r\n import Link from \"next/link\";\r\n import Nav from \"../Nav/Navbar\";\r\n"
                },
                {
                    "date": 1731253821686,
                    "content": "Index: \n===================================================================\n--- \n+++ \n@@ -0,0 +1,24 @@\n+\"use client\";\r\n+\r\n+import Link from \"next/link\";\r\n+import Nav from \"../Nav/Navbar\";\r\n+import Image from \"next/image\";\r\n+\r\n+const Header = () => {\r\n+  return (\r\n+    <header className=\"header\">\r\n+      <div className=\"container\">\r\n+\r\n+        {/* Navbar */}\r\n+        <div className=\"navbar\">\r\n+          <Nav />\r\n+          <Link href=\"/contact\">\r\n+            <button className=\"hire-button\">Hire me</button>\r\n+          </Link>\r\n+        </div>\r\n+      </div>\r\n+    </header>\r\n+  );\r\n+};\r\n+\r\n+export default Header;\n\\ No newline at end of file\n"
                },
                {
                    "date": 1731253827592,
                    "content": "Index: \n===================================================================\n--- \n+++ \n@@ -0,0 +1,23 @@\n+\"use client\";\r\n+\r\n+import Link from \"next/link\";\r\n+import Nav from \"../Nav/Navbar\";\r\n+\r\n+const Header = () => {\r\n+  return (\r\n+    <header className=\"header\">\r\n+      <div className=\"container\">\r\n+\r\n+        {/* Navbar */}\r\n+        <div className=\"navbar\">\r\n+          <Nav />\r\n+          <Link href=\"/contact\">\r\n+            <button className=\"hire-button\">Hire me</button>\r\n+          </Link>\r\n+        </div>\r\n+      </div>\r\n+    </header>\r\n+  );\r\n+};\r\n+\r\n+export default Header;\n\\ No newline at end of file\n"
                }
            ],
            "date": 1731248981264,
            "name": "Commit-0",
            "content": "\"use client\"; \r\n\r\nimport Link from \"next/link\";\r\nimport Nav from \"../Nav/Navbar\"; // Assuming Nav is a custom component.\r\nimport MobileNav from \"../MobileNav\"; // Assuming MobileNav is a custom component.\r\nimport Image from \"next/image\"; \r\nimport './Header.css'; // Import the custom CSS for this component\r\n\r\nconst Header = () => {\r\n  return (\r\n    <header className=\"header\">\r\n      <div className=\"container\">\r\n\r\n        {/* Link with Logo Image */}\r\n        <Link href=\"/\">\r\n          <Image\r\n            src=\"/logo.jpeg\" \r\n            alt=\"Aliza Logo\"\r\n            width={115} \r\n            height={60}\r\n            priority \r\n          />\r\n        </Link>\r\n\r\n        {/* Navbar */}\r\n        <div className=\"navbar\">\r\n          <Nav />\r\n          <Link href='/contact'>\r\n            <button className=\"hire-button\">Hire me</button>\r\n          </Link>\r\n        </div>\r\n\r\n        {/* Mobile Nav */}\r\n        <div className=\"mobile-nav\"> \r\n           <MobileNav /> \r\n        </div>\r\n\r\n      </div>\r\n    </header>\r\n  );\r\n};\r\n\r\nexport default Header;\r\n"
        }
    ]
}